README.rst
setup.py
Flask_CMDB.egg-info/PKG-INFO
Flask_CMDB.egg-info/SOURCES.txt
Flask_CMDB.egg-info/dependency_links.txt
Flask_CMDB.egg-info/not-zip-safe
Flask_CMDB.egg-info/requires.txt
Flask_CMDB.egg-info/top_level.txt
flask_cmdb/__init__.py