Metadata-Version: 1.1
Name: Flask-CMDB
Version: 0.1.4
Summary: A cmdb api client for Flask applications.
Home-page: https://github.com/lufeng4828/flask_cmdb
Author: Feng Lu
Author-email: lufeng044@qq.com
License: BSD
Platform: any
Classifier: Development Status :: 4 - Beta
Classifier: Environment :: Web Environment
Classifier: Intended Audience :: Developers
Classifier: License :: OSI Approved :: BSD License
Classifier: Operating System :: OS Independent
Classifier: Programming Language :: Python
Classifier: Topic :: Internet :: WWW/HTTP :: Dynamic Content
Classifier: Topic :: Software Development :: Libraries :: Python Modules
